lingcorp/__init__.py
lingcorp/annotator.py
lingcorp/cli/__init__.py
lingcorp/cli/annotator.py
lingcorp/config.py
lingcorp/cql.py
lingcorp/helpers.py
lingcorp/project_template/cookiecutter.json
lingcorp/project_template/{{cookiecutter.project_name}}/conf.py
lingcorp/project_template/{{cookiecutter.project_name}}/parsers.py
lingcorp/search.py
lingcorp/server.py
lingcorp/static/css/annotation.css
lingcorp/static/css/concordance.css
lingcorp/static/css/lingcorp.css
lingcorp/static/css/styles.css
lingcorp/static/js/annotation.js
lingcorp/static/js/concordance.js
lingcorp/static/js/scripts.js
lingcorp/templates/annotation.html
lingcorp/templates/base.html
lingcorp/templates/bench.html
lingcorp/templates/concordance.html
lingcorp/templates/record.html
lingcorp/templates/rich_record.html
lingcorp-0.1.3.dist-info/LICENSE
lingcorp-0.1.3.dist-info/METADATA
lingcorp-0.1.3.dist-info/WHEEL
lingcorp-0.1.3.dist-info/entry_points.txt
lingcorp-0.1.3.dist-info/RECORD
